simple_spider_tool/__init__.py
simple_spider_tool/date.py
simple_spider_tool/decorator.py
simple_spider_tool/hash.py
simple_spider_tool/jsons.py
simple_spider_tool/re.py
simple_spider_tool/types.py
simple_spider_tool-0.0.19.dist-info/METADATA
simple_spider_tool-0.0.19.dist-info/WHEEL
simple_spider_tool-0.0.19.dist-info/licenses/LICENSE
simple_spider_tool-0.0.19.dist-info/RECORD
