Metadata-Version: 2.1
Name: simple-spider-tool
Version: 0.0.19
Summary: 一些简易、好用的爬虫工具，减少代码与文件冗余，提升工作的效率和代码整洁度
Author-email: xingc <xingcys@gmail.com>
License-Expression: MIT
License-File: LICENSE
Keywords: datetime,jsonpath,md5,spider,timestamp,tool
Classifier: License :: OSI Approved :: MIT License
Classifier: Operating System :: OS Independent
Classifier: Programming Language :: Python :: 3
Classifier: Programming Language :: Python :: 3.5
Classifier: Programming Language :: Python :: 3.6
Classifier: Programming Language :: Python :: 3.7
Classifier: Programming Language :: Python :: 3.8
Classifier: Programming Language :: Python :: 3.9
Requires-Python: >=3.5
Requires-Dist: jsonpath>=0.82
Provides-Extra: seventeen
Requires-Dist: simple-spider-tool17; extra == 'seventeen'
